intake_solr/__init__.py
intake_solr/_version.py
intake_solr/source.py
tests/__init__.py
tests/sample1.csv
tests/test_discovery.py
tests/test_intake_solr.py
tests/util.py
intake_solr-0.1.1.dist-info/LICENSE
intake_solr-0.1.1.dist-info/METADATA
intake_solr-0.1.1.dist-info/WHEEL
intake_solr-0.1.1.dist-info/entry_points.txt
intake_solr-0.1.1.dist-info/top_level.txt
intake_solr-0.1.1.dist-info/RECORD
